setup.py
PyMissingData/__init__.py
PyMissingData/bayesian_learner.py
PyMissingData/compare_tools.py
PyMissingData/main.py
PyMissingData.egg-info/PKG-INFO
PyMissingData.egg-info/SOURCES.txt
PyMissingData.egg-info/dependency_links.txt
PyMissingData.egg-info/top_level.txt
PyMissingData/libpgm_static/__init__.py
PyMissingData/libpgm_static/dictionary.py
PyMissingData/libpgm_static/discretebayesiannetwork.py
PyMissingData/libpgm_static/dyndiscbayesiannetwork.py
PyMissingData/libpgm_static/graphskeleton.py
PyMissingData/libpgm_static/hybayesiannetwork.py
PyMissingData/libpgm_static/lgbayesiannetwork.py
PyMissingData/libpgm_static/nodedata.py
PyMissingData/libpgm_static/orderedskeleton.py
PyMissingData/libpgm_static/pgmlearner.py
PyMissingData/libpgm_static/sampleaggregator.py
PyMissingData/libpgm_static/tablecpdfactor.py
PyMissingData/libpgm_static/tablecpdfactorization.py
PyMissingData/libpgm_static/CPDtypes/__init__.py
PyMissingData/libpgm_static/CPDtypes/crazy.py
PyMissingData/libpgm_static/CPDtypes/discrete.py
PyMissingData/libpgm_static/CPDtypes/lg.py
PyMissingData/libpgm_static/CPDtypes/lgandd.py