Metadata-Version: 1.1
Name: PyMissingData
Version: 1.1.2
Summary: An approach based on Bayesian Networks to fill missing values
Home-page: http://arsandov.github.io/PyMissingData
Author: Augusto Sandoval
Author-email: augustocsandoval@gmail.com
License: Harvard University
Download-URL: https://github.com/arsandov/PyMissingData/releases/tag/1.1.2
Keywords: Missing Values,Machine Learning,Bayesian Networks
Platform: UNKNOWN
Classifier: Development Status :: 3 - Alpha
Classifier: Intended Audience :: Science/Research
Classifier: Topic :: Scientific/Engineering :: Astronomy
Classifier: Topic :: Software Development :: Build Tools
Classifier: Topic :: Software Development :: Libraries :: Python Modules
Classifier: Programming Language :: Python :: 2
Classifier: Programming Language :: Python :: 2.6
Classifier: Programming Language :: Python :: 2.7
